{
  "dataset": "nq",
  "num_examples": 79168,
  "num_signatures": 1086,
  "answer_form_distribution": {
    "entity_or_short_span": 49940,
    "year_or_date": 15436,
    "number": 6952,
    "long_span": 5295,
    "list_like": 1543,
    "boolean": 2
  },
  "wh_distribution": {
    "who": 31348,
    "when": 16490,
    "what": 9514,
    "other": 9282,
    "where": 6478,
    "how": 4234,
    "which": 1568,
    "is": 161,
    "do": 17,
    "whose": 17,
    "does": 16,
    "are": 16,
    "was": 14,
    "did": 7,
    "whom": 3,
    "were": 3
  },
  "entity_distribution": {
    "single_entity": 79168
  },
  "token_distribution": {
    "medium": 68015,
    "long": 10792,
    "very_long": 325,
    "short": 36
  },
  "flag_distribution": {
    "direct_lookup": 79168,
    "person": 33111,
    "numeric": 23760,
    "temporal": 18029,
    "title_work": 10837,
    "location": 10351,
    "quoted_span": 6537,
    "long_question": 2197,
    "organization": 1184,
    "yes_no": 234,
    "alias": 202
  },
  "default_target_size": 3000,
  "original_size": 79168,
  "target_size": 3000,
  "selected_size": 3000,
  "selected_ratio": 0.037894098625707355,
  "unique_signatures_original": 1086,
  "unique_signatures_selected": 769,
  "cap_per_signature": 12,
  "protect_signature_freq_leq": 3,
  "rare_label_threshold": 159,
  "protected_examples": 949,
  "answer_form_selected": {
    "entity_or_short_span": 1340,
    "long_span": 537,
    "number": 504,
    "list_like": 352,
    "year_or_date": 265,
    "boolean": 2
  },
  "wh_selected": {
    "other": 677,
    "which": 459,
    "what": 413,
    "who": 381,
    "how": 339,
    "where": 317,
    "when": 249,
    "is": 72,
    "do": 17,
    "whose": 17,
    "does": 16,
    "are": 16,
    "was": 14,
    "did": 7,
    "were": 3,
    "whom": 3
  },
  "entity_selected": {
    "single_entity": 3000
  },
  "token_selected": {
    "long": 1428,
    "medium": 1336,
    "very_long": 200,
    "short": 36
  },
  "flag_selected": {
    "direct_lookup": 3000,
    "numeric": 978,
    "location": 907,
    "long_question": 893,
    "quoted_span": 667,
    "person": 639,
    "title_work": 609,
    "organization": 588,
    "temporal": 495,
    "yes_no": 145,
    "alias": 97
  },
  "label_coverage_selected": {
    "entity:single_entity": 3000,
    "flag:direct_lookup": 3000,
    "token:long": 1428,
    "answer:entity_or_short_span": 1340,
    "token:medium": 1336,
    "flag:numeric": 978,
    "flag:location": 907,
    "flag:long_question": 893,
    "wh:other": 677,
    "flag:quoted_span": 667,
    "flag:person": 639,
    "flag:title_work": 609,
    "flag:organization": 588,
    "answer:long_span": 537,
    "answer:number": 504,
    "flag:temporal": 495,
    "wh:which": 459,
    "wh:what": 413,
    "wh:who": 381,
    "answer:list_like": 352,
    "wh:how": 339,
    "wh:where": 317,
    "answer:year_or_date": 265,
    "wh:when": 249,
    "token:very_long": 200,
    "flag:yes_no": 145,
    "flag:alias": 97,
    "wh:is": 72,
    "token:short": 36,
    "wh:do": 17
  }
}